numpry/__init__.py
numerosPrimosFP5-0.1.dist-info/LICENSE
numerosPrimosFP5-0.1.dist-info/METADATA
numerosPrimosFP5-0.1.dist-info/WHEEL
numerosPrimosFP5-0.1.dist-info/top_level.txt
numerosPrimosFP5-0.1.dist-info/RECORD
