Metadata-Version: 2.1
Name: numerosPrimosFP5
Version: 0.1
Summary: Tool to calculate Prime Numbers from 1 to n
Home-page: UNKNOWN
Author: Facundo Stettler
Author-email: stettlerfacundo@gmail.com
License: GNU GPLV3
Keywords: prime numbers numeros primos
Platform: UNKNOWN
Classifier: Development Status :: 4 - Beta
Classifier: Intended Audience :: Developers
Classifier: Topic :: Utilities
Classifier: License :: OSI Approved :: GNU General Public License v3 (GPLv3)
Classifier: Programming Language :: Python :: 3
Classifier: Operating System :: OS Independent
